<data>
<text0><![CDATA[<font color="#980101"><B>Root Cause Analysis:</B> Summary</font>]]></text0>
<text1><![CDATA[<B>The RSV Web-based Tool</B>]]></text1>
<text2><![CDATA[Welcome to your web-based Readiness Skills Verification program!<br><br>This tool provides an interactive environment that assesses perishable BE skills through knowledge-based test questions and response-oriented scenarios.<br><br>Once you're through with this introduction, you'll be able to begin your verification process by selecting the first assessment from the list in the Med+Learn course window.]]></text2>

</data>