<data>
<text0><![CDATA[<font color="#980101"><B>Root Cause Analysis:</B> Summary</font>]]></text0>
<text1><![CDATA[<B>Part I:  Assessing the Situation</B>]]></text1>
<text2><![CDATA[Before reaching back for radiological consultation, you call the BE Office to send additional support to the ECP.  You also send one BE Tech to the hospital to conduct interviews and assist with other activities related to the possible exposure to the damage assessment team and first responders.<br><br>You have remaining team members conduct research about the health effects of the isotopes included on the RAM Permit, given that there is an unknown item that was not included on the inventory.]]></text2>
<text3><![CDATA[Major Fletcher agreed with your recommendation to contact the ESOH Service Center to get guidance from the Radiation Health Branch or AFRAT.<br><br>Before he contacts the ESOH Service Center, he calls the BE Office to send additional support to the ECP.  He also sends one BE Tech to the hospital to conduct interviews and assist with other activities related to the possible exposure to the damage assessment team and first responders.<br><br>He has remaining team members conduct research about the health effects of the isotopes included on the RAM Permit, given that there is an unknown item that was not included on the inventory.]]></text3>
<transcript_text><![CDATA[Default Transcript]]></transcript_text>
</data>